<annotation>
	<folder>all</folder>
	<filename>manaoag_church_0018.jpg</filename>
	<path>C:\Users\00ant\Desktop\images\all\manaoag_church_0018.jpg</path>
	<source>
		<database>Unknown</database>
	</source>
	<size>
		<width>275</width>
		<height>183</height>
		<depth>3</depth>
	</size>
	<segmented>0</segmented>
	<object>
		<name>manaoag_church_manaoag_pangasinan</name>
		<pose>Unspecified</pose>
		<truncated>0</truncated>
		<difficult>0</difficult>
		<bndbox>
			<xmin>56</xmin>
			<ymin>10</ymin>
			<xmax>172</xmax>
			<ymax>149</ymax>
		</bndbox>
	</object>
</annotation>