<annotation>
	<folder>all</folder>
	<filename>taal_basilica_church_0039.jpg</filename>
	<path>C:\Users\00ant\Desktop\images\all\taal_basilica_church_0039.jpg</path>
	<source>
		<database>Unknown</database>
	</source>
	<size>
		<width>640</width>
		<height>336</height>
		<depth>3</depth>
	</size>
	<segmented>0</segmented>
	<object>
		<name>taal_basilica_church_taal_batangas</name>
		<pose>Unspecified</pose>
		<truncated>1</truncated>
		<difficult>0</difficult>
		<bndbox>
			<xmin>27</xmin>
			<ymin>3</ymin>
			<xmax>602</xmax>
			<ymax>336</ymax>
		</bndbox>
	</object>
</annotation>
